taskmessenger/__init__.py
taskmessenger/_server_location.py
taskmessenger/py.typed
taskmessenger/send.py
taskmessenger-1.0.2.dist-info/LICENSE
taskmessenger-1.0.2.dist-info/METADATA
taskmessenger-1.0.2.dist-info/WHEEL
taskmessenger-1.0.2.dist-info/top_level.txt
taskmessenger-1.0.2.dist-info/RECORD
