Metadata-Version: 2.1
Name: taskmessenger
Version: 1.0.2
Summary: Write emails after finishing a task
Home-page: UNKNOWN
Author: Armaan Ahmed
License: MIT
Project-URL: GitHub, https://github.com/ArmaanAhmed22/TaskMessenger/
Project-URL: BugTracker, https://github.com/ArmaanAhmed22/TaskMessenger/issues
Platform: unix
Platform: linux
Platform: osx
Platform: win32
Classifier: Programming Language :: Python :: 3
Classifier: License :: OSI Approved :: MIT License
Classifier: Operating System :: OS Independent
Requires-Python: >=3.6
License-File: LICENSE
Requires-Dist: requests (>=2)
Requires-Dist: types-requests (>=2)
Provides-Extra: testing
Requires-Dist: pytest (>=6.0) ; extra == 'testing'
Requires-Dist: pytest-cov (>=2.0) ; extra == 'testing'
Requires-Dist: mypy (>=0.910) ; extra == 'testing'
Requires-Dist: flake8 (>=3.9) ; extra == 'testing'
Requires-Dist: tox (>=3.24) ; extra == 'testing'
